[
  {
    "featureType": "administrative",
    "elementType": "labels.text.fill",
    "stylers": [
      {
        "color": "#444444"
      }
    ]
  },
  {
    "featureType": "landscape",
    "elementType": "all",
    "stylers": [
      {
        "color": "#f2f2f2"
      }
    ]
  },
  {
    "featureType": "poi",
    "elementType": "all",
    "stylers": [
      {
        "visibility": "off"
      }
    ]
  },
  {
    "featureType": "poi.business",
    "elementType": "all",
    "stylers": [
      {
        "visibility": "off"
      }
    ]
  },
  {
    "featureType": "poi.park",
    "elementType": "geometry.fill",
    "stylers": [
      {
        "visibility": "on"
      },
      {
        "saturation": "37"
      },
      {
        "hue": "#00ff3d"
      },
      {
        "gamma": "0.60"
      }
    ]
  },
  {
    "featureType": "poi.park",
    "elementType": "labels",
    "stylers": [
      {
        "visibility": "on"
      }
    ]
  },
  {
    "featureType": "poi.park",
    "elementType": "labels.text",
    "stylers": [
      {
        "visibility": "on"
      }
    ]
  },
  {
    "featureType": "road",
    "elementType": "all",
    "stylers": [
      {
        "saturation": -100
      },
      {
        "lightness": 45
      }
    ]
  },
  {
    "featureType": "road.highway",
    "elementType": "all",
    "stylers": [
      {
        "visibility": "simplified"
      }
    ]
  },
  {
    "featureType": "road.highway.controlled_access",
    "elementType": "all",
    "stylers": [
      {
        "visibility": "on"
      },
      {
        "gamma": "1.07"
      },
      {
        "lightness": "0"
      }
    ]
  },
  {
    "featureType": "road.arterial",
    "elementType": "labels.icon",
    "stylers": [
      {
        "visibility": "off"
      }
    ]
  },
  {
    "featureType": "transit",
    "elementType": "all",
    "stylers": [
      {
        "visibility": "off"
      }
    ]
  },
  {
    "featureType": "transit.line",
    "elementType": "all",
    "stylers": [
      {
        "visibility": "on"
      }
    ]
  },
  {
    "featureType": "transit.station",
    "elementType": "all",
    "stylers": [
      {
        "visibility": "on"
      }
    ]
  },
  {
    "featureType": "transit.station.airport",
    "elementType": "all",
    "stylers": [
      {
        "visibility": "on"
      }
    ]
  },
  {
    "featureType": "transit.station.bus",
    "elementType": "all",
    "stylers": [
      {
        "visibility": "on"
      }
    ]
  },
  {
    "featureType": "transit.station.rail",
    "elementType": "all",
    "stylers": [
      {
        "visibility": "on"
      }
    ]
  },
  {
    "featureType": "water",
    "elementType": "all",
    "stylers": [
      {
        "color": "#46bcec"
      },
      {
        "visibility": "on"
      }
    ]
  },
  {
    "featureType": "water",
    "elementType": "labels",
    "stylers": [
      {
        "visibility": "off"
      },
      {
        "hue": "#ff0000"
      }
    ]
  },
  {
    "featureType": "water",
    "elementType": "labels.text",
    "stylers": [
      {
        "visibility": "on"
      },
      {
        "color": "#ffffff"
      }
    ]
  }
]